{"2024-01-30-2024-01-30": {"MEX - Cuajimalpa - FB": [{"valor": 1, "palabra": "mundial-educación-ambiental"}, {"valor": 1, "palabra": "educación-ambiental-recibimos"}, {"valor": 1, "palabra": "ambiental-recibimos-vivero"}, {"valor": 1, "palabra": "recibimos-vivero-forestal"}, {"valor": 1, "palabra": "vivero-forestal-unidad"}, {"valor": 1, "palabra": "forestal-unidad-manejo"}, {"valor": 1, "palabra": "unidad-manejo-ambiental"}, {"valor": 1, "palabra": "manejo-ambiental-peteretes"}, {"valor": 1, "palabra": "ambiental-peteretes-alumnas"}, {"valor": 1, "palabra": "peteretes-alumnas-alumnos"}, {"valor": 1, "palabra": "alumnas-alumnos-padres"}, {"valor": 1, "palabra": "alumnos-padres-madres"}, {"valor": 1, "palabra": "padres-madres-familia"}, {"valor": 1, "palabra": "madres-familia-personal"}, {"valor": 1, "palabra": "familia-personal-docente"}, {"valor": 1, "palabra": "personal-docente-jardín"}, {"valor": 1, "palabra": "docente-jardín-alfonso"}, {"valor": 1, "palabra": "jardín-alfonso-sierra"}, {"valor": 1, "palabra": "alfonso-sierra-partida"}, {"valor": 1, "palabra": "sierra-partida-gracias"}, {"valor": 1, "palabra": "partida-gracias-visita"}, {"valor": 1, "palabra": "gracias-visita-enseñar"}, {"valor": 1, "palabra": "visita-enseñar-educación"}, {"valor": 1, "palabra": "enseñar-educación-ambiental"}, {"valor": 1, "palabra": "educación-ambiental-enseñar"}, {"valor": 1, "palabra": "ambiental-enseñar-valorar"}, {"valor": 1, "palabra": "enseñar-valorar-adrian"}, {"valor": 1, "palabra": "valorar-adrian-rubalcava"}, {"valor": 1, "palabra": "adrian-rubalcava-alcaldía"}, {"valor": 1, "palabra": "rubalcava-alcaldía-cuajimalpa"}], "MEX - Azcapotzalco - FB": [{"valor": 2, "palabra": "alcaldesa-margarita-saldaña"}, {"valor": 1, "palabra": "margarita-saldaña-alcaldía"}, {"valor": 1, "palabra": "saldaña-alcaldía-azcapotzalco"}, {"valor": 1, "palabra": "alcaldía-azcapotzalco-firmemente"}, {"valor": 1, "palabra": "azcapotzalco-firmemente-comprometidos"}, {"valor": 1, "palabra": "firmemente-comprometidos-fomento"}, {"valor": 1, "palabra": "comprometidos-fomento-cultura"}, {"valor": 1, "palabra": "fomento-cultura-salvaguarda"}, {"valor": 1, "palabra": "cultura-salvaguarda-nuestras"}, {"valor": 1, "palabra": "salvaguarda-nuestras-tradiciones"}, {"valor": 1, "palabra": "nuestras-tradiciones-tepanecas"}, {"valor": 1, "palabra": "tradiciones-tepanecas-trabajamos"}, {"valor": 1, "palabra": "tepanecas-trabajamos-unidos"}, {"valor": 1, "palabra": "trabajamos-unidos-preservar"}, {"valor": 1, "palabra": "unidos-preservar-enriquecer"}, {"valor": 1, "palabra": "preservar-enriquecer-nuestro"}, {"valor": 1, "palabra": "enriquecer-nuestro-invaluable"}, {"valor": 1, "palabra": "nuestro-invaluable-patrimonio"}, {"valor": 1, "palabra": "invaluable-patrimonio-cultural"}, {"valor": 1, "palabra": "patrimonio-cultural-sigamos"}, {"valor": 1, "palabra": "cultural-sigamos-construyendo"}, {"valor": 1, "palabra": "sigamos-construyendo-juntos"}, {"valor": 1, "palabra": "construyendo-juntos-azcapotzalco"}, {"valor": 1, "palabra": "juntos-azcapotzalco-historia"}, {"valor": 1, "palabra": "azcapotzalco-historia-tradición"}, {"valor": 1, "palabra": "historia-tradición-finalizó"}, {"valor": 1, "palabra": "tradición-finalizó-primer"}, {"valor": 1, "palabra": "finalizó-primer-construcción"}, {"valor": 1, "palabra": "primer-construcción-plafones"}, {"valor": 1, "palabra": "construcción-plafones-tablaroca"}], "MEX - Miguel Hidalgo - FB": [{"valor": 3, "palabra": "alcalde-mauricio-echartea"}, {"valor": 2, "palabra": "juegos-ciudad-méxico"}, {"valor": 1, "palabra": "alcaldía-servicio-regresan"}, {"valor": 1, "palabra": "servicio-regresan-dinero"}, {"valor": 1, "palabra": "regresan-dinero-alcanza"}, {"valor": 1, "palabra": "dinero-alcanza-modernizar"}, {"valor": 1, "palabra": "alcanza-modernizar-gobierno"}, {"valor": 1, "palabra": "modernizar-gobierno-cuarta"}, {"valor": 1, "palabra": "gobierno-cuarta-espalda"}, {"valor": 1, "palabra": "cuarta-espalda-miguel"}, {"valor": 1, "palabra": "espalda-miguel-hidalgo"}, {"valor": 1, "palabra": "miguel-hidalgo-equipo"}, {"valor": 1, "palabra": "hidalgo-equipo-alcaldía"}, {"valor": 1, "palabra": "equipo-alcaldía-miguel"}, {"valor": 1, "palabra": "alcaldía-miguel-hidalgo"}, {"valor": 1, "palabra": "miguel-hidalgo-haciendo"}, {"valor": 1, "palabra": "hidalgo-haciendo-esfuerzo"}, {"valor": 1, "palabra": "haciendo-esfuerzo-nuevas"}, {"valor": 1, "palabra": "esfuerzo-nuevas-experiencias"}, {"valor": 1, "palabra": "nuevas-experiencias-nuestros"}, {"valor": 1, "palabra": "experiencias-nuestros-paseos"}, {"valor": 1, "palabra": "nuestros-paseos-ciclistas"}, {"valor": 1, "palabra": "paseos-ciclistas-pierdas"}, {"valor": 1, "palabra": "ciclistas-pierdas-febrero"}, {"valor": 1, "palabra": "pierdas-febrero-porque"}, {"valor": 1, "palabra": "febrero-porque-tendremos"}, {"valor": 1, "palabra": "porque-tendremos-muchas"}, {"valor": 1, "palabra": "tendremos-muchas-sorpresas"}, {"valor": 1, "palabra": "muchas-sorpresas-estamos"}, {"valor": 1, "palabra": "sorpresas-estamos-orgullosos"}]}, "2024-01-31-2024-01-31": {"MEX - Cuajimalpa - FB": [{"valor": 1, "palabra": "tradición-invita-tienes"}, {"valor": 1, "palabra": "invita-tienes-alguna"}, {"valor": 1, "palabra": "tienes-alguna-demarcaciones"}, {"valor": 1, "palabra": "alguna-demarcaciones-ejidos"}, {"valor": 1, "palabra": "demarcaciones-ejidos-oportunidad"}, {"valor": 1, "palabra": "ejidos-oportunidad-nosotros"}, {"valor": 1, "palabra": "oportunidad-nosotros-historia"}, {"valor": 1, "palabra": "nosotros-historia-alcaldia"}, {"valor": 1, "palabra": "historia-alcaldia-xochimilco"}, {"valor": 1, "palabra": "alcaldia-xochimilco-adrian"}, {"valor": 1, "palabra": "xochimilco-adrian-rubalcava"}, {"valor": 1, "palabra": "adrian-rubalcava-carlos"}, {"valor": 1, "palabra": "rubalcava-carlos-segura"}], "MEX - Azcapotzalco - FB": [{"valor": 2, "palabra": "alcaldesa-margarita-saldaña"}, {"valor": 2, "palabra": "margarita-saldaña-equipo"}, {"valor": 1, "palabra": "descubre-importancia-jardines"}, {"valor": 1, "palabra": "importancia-jardines-polinizadores"}, {"valor": 1, "palabra": "jardines-polinizadores-alcaldía"}, {"valor": 1, "palabra": "polinizadores-alcaldía-azcapotzalco"}, {"valor": 1, "palabra": "alcaldía-azcapotzalco-earthgonomic"}, {"valor": 1, "palabra": "azcapotzalco-earthgonomic-méxico"}, {"valor": 1, "palabra": "earthgonomic-méxico-acompáñanos"}, {"valor": 1, "palabra": "méxico-acompáñanos-iniciativa"}, {"valor": 1, "palabra": "acompáñanos-iniciativa-promueve"}, {"valor": 1, "palabra": "iniciativa-promueve-biodiversidad"}, {"valor": 1, "palabra": "promueve-biodiversidad-cuidado"}, {"valor": 1, "palabra": "biodiversidad-cuidado-ambiente"}, {"valor": 1, "palabra": "cuidado-ambiente-juntos"}, {"valor": 1, "palabra": "ambiente-juntos-contribuimos"}, {"valor": 1, "palabra": "juntos-contribuimos-espacios"}, {"valor": 1, "palabra": "contribuimos-espacios-sostenibles"}, {"valor": 1, "palabra": "espacios-sostenibles-conscientes"}, {"valor": 1, "palabra": "sostenibles-conscientes-encontraremos"}, {"valor": 1, "palabra": "conscientes-encontraremos-escuela"}, {"valor": 1, "palabra": "encontraremos-escuela-primaria"}, {"valor": 1, "palabra": "escuela-primaria-vicente"}, {"valor": 1, "palabra": "primaria-vicente-alcaraz"}, {"valor": 1, "palabra": "vicente-alcaraz-azcapotzalco"}, {"valor": 1, "palabra": "alcaraz-azcapotzalco-acompaña"}, {"valor": 1, "palabra": "azcapotzalco-acompaña-alcaldesa"}, {"valor": 1, "palabra": "acompaña-alcaldesa-margarita"}, {"valor": 1, "palabra": "saldaña-equipo-jornada"}, {"valor": 1, "palabra": "equipo-jornada-dedicada"}], "MEX - Miguel Hidalgo - FB": [{"valor": 2, "palabra": "alcalde-mauricio-echartea"}, {"valor": 1, "palabra": "reforzamos-vigilancia-verónica"}, {"valor": 1, "palabra": "vigilancia-verónica-anzures"}, {"valor": 1, "palabra": "verónica-anzures-oficiales"}, {"valor": 1, "palabra": "anzures-oficiales-estarán"}, {"valor": 1, "palabra": "oficiales-estarán-patrulla"}, {"valor": 1, "palabra": "estarán-patrulla-adquirieron"}, {"valor": 1, "palabra": "patrulla-adquirieron-nuestros"}, {"valor": 1, "palabra": "adquirieron-nuestros-vecinos"}, {"valor": 1, "palabra": "nuestros-vecinos-presupuesto"}, {"valor": 1, "palabra": "vecinos-presupuesto-participativo"}, {"valor": 1, "palabra": "presupuesto-participativo-nuestro"}, {"valor": 1, "palabra": "participativo-nuestro-equipo"}, {"valor": 1, "palabra": "nuestro-equipo-arrasa"}, {"valor": 1, "palabra": "equipo-arrasa-hacemos"}, {"valor": 1, "palabra": "arrasa-hacemos-también"}, {"valor": 1, "palabra": "hacemos-también-parque"}, {"valor": 1, "palabra": "también-parque-reforma"}, {"valor": 1, "palabra": "parque-reforma-social"}, {"valor": 1, "palabra": "reforma-social-iluminamos"}, {"valor": 1, "palabra": "social-iluminamos-dejamos"}, {"valor": 1, "palabra": "iluminamos-dejamos-bonito"}, {"valor": 1, "palabra": "dejamos-bonito-mantenimiento"}, {"valor": 1, "palabra": "bonito-mantenimiento-verdes"}, {"valor": 1, "palabra": "mantenimiento-verdes-famosas"}, {"valor": 1, "palabra": "verdes-famosas-chelerías"}, {"valor": 1, "palabra": "famosas-chelerías-permitidas"}, {"valor": 1, "palabra": "chelerías-permitidas-agradecemos"}, {"valor": 1, "palabra": "permitidas-agradecemos-operativos"}, {"valor": 1, "palabra": "agradecemos-operativos-secretaría"}]}, "2024-02-01-2024-02-01": {"MEX - Cuajimalpa - FB": [{"valor": 4, "palabra": "alcaldía-cuajimalpa-morelos"}, {"valor": 2, "palabra": "cuajimalpa-morelos-extiende"}, {"valor": 2, "palabra": "morelos-extiende-cordial"}, {"valor": 2, "palabra": "extiende-cordial-felicitación"}, {"valor": 2, "palabra": "motivo-cumpleaños-muchas"}, {"valor": 2, "palabra": "cumpleaños-muchas-felicidades"}, {"valor": 1, "palabra": "camilo-gracias-representar"}, {"valor": 1, "palabra": "gracias-representar-cuajimalpa"}, {"valor": 1, "palabra": "representar-cuajimalpa-adrian"}, {"valor": 1, "palabra": "cuajimalpa-adrian-rubalcava"}, {"valor": 1, "palabra": "adrian-rubalcava-sesión"}, {"valor": 1, "palabra": "rubalcava-sesión-ordinaria"}, {"valor": 1, "palabra": "sesión-ordinaria-concejo"}, {"valor": 1, "palabra": "ordinaria-concejo-alcaldía"}, {"valor": 1, "palabra": "concejo-alcaldía-cuajimalpa"}, {"valor": 1, "palabra": "cuajimalpa-morelos-atención"}, {"valor": 1, "palabra": "morelos-atención-prevención"}, {"valor": 1, "palabra": "atención-prevención-atención"}, {"valor": 1, "palabra": "prevención-atención-erradicación"}, {"valor": 1, "palabra": "atención-erradicación-violencia"}, {"valor": 1, "palabra": "erradicación-violencia-género"}, {"valor": 1, "palabra": "violencia-género-adrian"}, {"valor": 1, "palabra": "género-adrian-rubalcava"}, {"valor": 1, "palabra": "adrian-rubalcava-alcaldía"}, {"valor": 1, "palabra": "rubalcava-alcaldía-cuajimalpa"}, {"valor": 1, "palabra": "cordial-felicitación-motivo"}, {"valor": 1, "palabra": "felicitación-motivo-cumpleaños"}, {"valor": 1, "palabra": "muchas-felicidades-esperamos"}, {"valor": 1, "palabra": "felicidades-esperamos-viernes"}, {"valor": 1, "palabra": "esperamos-viernes-febrero"}], "MEX - Azcapotzalco - FB": [{"valor": 6, "palabra": "alcaldesa-margarita-saldaña"}, {"valor": 4, "palabra": "margarita-saldaña-equipo"}, {"valor": 2, "palabra": "febrero-azcapotzalco-potencia"}, {"valor": 1, "palabra": "felicidades-participantes-finalizó"}, {"valor": 1, "palabra": "participantes-finalizó-nuestro"}, {"valor": 1, "palabra": "finalizó-nuestro-construcción"}, {"valor": 1, "palabra": "nuestro-construcción-plafones"}, {"valor": 1, "palabra": "construcción-plafones-tablaroca"}, {"valor": 1, "palabra": "plafones-tablaroca-capacitados"}, {"valor": 1, "palabra": "tablaroca-capacitados-oficio"}, {"valor": 1, "palabra": "capacitados-oficio-abriendo"}, {"valor": 1, "palabra": "oficio-abriendo-puertas"}, {"valor": 1, "palabra": "abriendo-puertas-emocionantes"}, {"valor": 1, "palabra": "puertas-emocionantes-oportunidades"}, {"valor": 1, "palabra": "emocionantes-oportunidades-emprendimiento"}, {"valor": 1, "palabra": "oportunidades-emprendimiento-sigamos"}, {"valor": 1, "palabra": "emprendimiento-sigamos-construyendo"}, {"valor": 1, "palabra": "sigamos-construyendo-juntos"}, {"valor": 1, "palabra": "construyendo-juntos-camino"}, {"valor": 1, "palabra": "juntos-camino-aprendizaje"}, {"valor": 1, "palabra": "camino-aprendizaje-crecimiento"}, {"valor": 1, "palabra": "aprendizaje-crecimiento-vecinos"}, {"valor": 1, "palabra": "crecimiento-vecinos-presidente"}, {"valor": 1, "palabra": "vecinos-presidente-madero"}, {"valor": 1, "palabra": "presidente-madero-alcaldesa"}, {"valor": 1, "palabra": "madero-alcaldesa-margarita"}, {"valor": 1, "palabra": "saldaña-equipo-trabajo"}, {"valor": 1, "palabra": "equipo-trabajo-invitan"}, {"valor": 1, "palabra": "trabajo-invitan-febrero"}, {"valor": 1, "palabra": "invitan-febrero-candelaria"}], "MEX - Miguel Hidalgo - FB": [{"valor": 2, "palabra": "alcalde-mauricio-echartea"}, {"valor": 1, "palabra": "fortalece-vecinos-también"}, {"valor": 1, "palabra": "vecinos-también-unidad"}, {"valor": 1, "palabra": "también-unidad-patrullar"}, {"valor": 1, "palabra": "unidad-patrullar-colonia"}, {"valor": 1, "palabra": "patrullar-colonia-atender"}, {"valor": 1, "palabra": "colonia-atender-oportunamente"}, {"valor": 1, "palabra": "atender-oportunamente-llamados"}, {"valor": 1, "palabra": "oportunamente-llamados-cualquier"}, {"valor": 1, "palabra": "llamados-cualquier-actividad"}, {"valor": 1, "palabra": "cualquier-actividad-sospechosa"}, {"valor": 1, "palabra": "actividad-sospechosa-batres"}, {"valor": 1, "palabra": "sospechosa-batres-buenos"}, {"valor": 1, "palabra": "batres-buenos-resultados"}, {"valor": 1, "palabra": "buenos-resultados-seguridad"}, {"valor": 1, "palabra": "resultados-seguridad-logros"}, {"valor": 1, "palabra": "seguridad-logros-alcaldías"}, {"valor": 1, "palabra": "logros-alcaldías-gobierno"}, {"valor": 1, "palabra": "alcaldías-gobierno-entonces"}, {"valor": 1, "palabra": "gobierno-entonces-mejora"}, {"valor": 1, "palabra": "entonces-mejora-seguridad"}, {"valor": 1, "palabra": "mejora-seguridad-alcaldías"}, {"valor": 1, "palabra": "seguridad-alcaldías-gobierna"}, {"valor": 1, "palabra": "alcaldías-gobierna-oposición"}, {"valor": 1, "palabra": "gobierna-oposición-empeora"}, {"valor": 1, "palabra": "oposición-empeora-gobierna"}, {"valor": 1, "palabra": "empeora-gobierna-morena"}, {"valor": 1, "palabra": "gobierna-morena-alcalde"}, {"valor": 1, "palabra": "morena-alcalde-mauricio"}, {"valor": 1, "palabra": "mauricio-echartea-supervisa"}]}, "2024-02-02-2024-02-02": {"MEX - Cuajimalpa - FB": [{"valor": 1, "palabra": "convento-desierto-leones"}, {"valor": 1, "palabra": "desierto-leones-patrimonio"}, {"valor": 1, "palabra": "leones-patrimonio-arquitectónico"}, {"valor": 1, "palabra": "patrimonio-arquitectónico-cultural"}, {"valor": 1, "palabra": "arquitectónico-cultural-místico"}, {"valor": 1, "palabra": "cultural-místico-lugares"}, {"valor": 1, "palabra": "místico-lugares-hermosos"}, {"valor": 1, "palabra": "lugares-hermosos-visitar"}, {"valor": 1, "palabra": "hermosos-visitar-familia"}, {"valor": 1, "palabra": "visitar-familia-semanaorgullosamente"}, {"valor": 1, "palabra": "familia-semanaorgullosamente-adrian"}, {"valor": 1, "palabra": "semanaorgullosamente-adrian-rubalcava"}, {"valor": 1, "palabra": "adrian-rubalcava-lamentamos"}, {"valor": 1, "palabra": "rubalcava-lamentamos-profundamente"}, {"valor": 1, "palabra": "lamentamos-profundamente-fallecimiento"}, {"valor": 1, "palabra": "profundamente-fallecimiento-estadounidense"}, {"valor": 1, "palabra": "fallecimiento-estadounidense-jugador"}, {"valor": 1, "palabra": "estadounidense-jugador-futbol"}, {"valor": 1, "palabra": "jugador-futbol-americano"}, {"valor": 1, "palabra": "futbol-americano-weathers"}, {"valor": 1, "palabra": "americano-weathers-nuestro"}, {"valor": 1, "palabra": "weathers-nuestro-sincero"}, {"valor": 1, "palabra": "nuestro-sincero-pésame"}, {"valor": 1, "palabra": "sincero-pésame-comisión"}, {"valor": 1, "palabra": "pésame-comisión-derechos"}, {"valor": 1, "palabra": "comisión-derechos-humanos"}, {"valor": 1, "palabra": "derechos-humanos-ciudad"}, {"valor": 1, "palabra": "humanos-ciudad-méxico"}, {"valor": 1, "palabra": "ciudad-méxico-estará"}, {"valor": 1, "palabra": "méxico-estará-brindando"}], "MEX - Azcapotzalco - FB": [{"valor": 4, "palabra": "alcaldesa-margarita-saldaña"}, {"valor": 4, "palabra": "margarita-saldaña-equipo"}, {"valor": 4, "palabra": "saldaña-equipo-recorrido"}, {"valor": 4, "palabra": "escuchando-atendiendo-peticiones"}, {"valor": 3, "palabra": "equipo-recorrido-unidad"}, {"valor": 3, "palabra": "acompaña-alcaldesa-margarita"}, {"valor": 3, "palabra": "estaremos-escuchando-atendiendo"}, {"valor": 2, "palabra": "acompáñame-transmisión-entrega"}, {"valor": 2, "palabra": "transmisión-entrega-trabajos"}, {"valor": 2, "palabra": "repavimentación-concreto-hidráulico"}, {"valor": 2, "palabra": "evento-materia-protección"}, {"valor": 2, "palabra": "atendiendo-peticiones-vecinos"}, {"valor": 2, "palabra": "recorrido-unidad-estaremos"}, {"valor": 2, "palabra": "unidad-estaremos-escuchando"}, {"valor": 1, "palabra": "entrega-trabajos-recuperación"}, {"valor": 1, "palabra": "trabajos-recuperación-integral"}, {"valor": 1, "palabra": "recuperación-integral-palzaleta"}, {"valor": 1, "palabra": "integral-palzaleta-presidentes"}, {"valor": 1, "palabra": "palzaleta-presidentes-madero"}, {"valor": 1, "palabra": "presidentes-madero-azcapotzalco"}, {"valor": 1, "palabra": "madero-azcapotzalco-celebramos"}, {"valor": 1, "palabra": "azcapotzalco-celebramos-entrega"}, {"valor": 1, "palabra": "celebramos-entrega-repavimentación"}, {"valor": 1, "palabra": "entrega-repavimentación-concreto"}, {"valor": 1, "palabra": "concreto-hidráulico-jicama"}, {"valor": 1, "palabra": "hidráulico-jicama-ignación"}, {"valor": 1, "palabra": "jicama-ignación-allende"}, {"valor": 1, "palabra": "ignación-allende-gracias"}, {"valor": 1, "palabra": "allende-gracias-paciencia"}, {"valor": 1, "palabra": "gracias-paciencia-durante"}], "MEX - Miguel Hidalgo - FB": [{"valor": 1, "palabra": "tamalizas-podían-faltar"}, {"valor": 1, "palabra": "podían-faltar-miguel"}, {"valor": 1, "palabra": "faltar-miguel-hidalgo"}, {"valor": 1, "palabra": "miguel-hidalgo-puesto"}, {"valor": 1, "palabra": "hidalgo-puesto-muchas"}, {"valor": 1, "palabra": "puesto-muchas-gracias"}, {"valor": 1, "palabra": "muchas-gracias-vecinos"}, {"valor": 1, "palabra": "gracias-vecinos-varias"}, {"valor": 1, "palabra": "vecinos-varias-colonias"}, {"valor": 1, "palabra": "varias-colonias-invitado"}, {"valor": 1, "palabra": "colonias-invitado-celebrar"}, {"valor": 1, "palabra": "invitado-celebrar-tradición"}, {"valor": 1, "palabra": "celebrar-tradición-nuestro"}, {"valor": 1, "palabra": "tradición-nuestro-equipo"}, {"valor": 1, "palabra": "nuestro-equipo-sorpresas"}, {"valor": 1, "palabra": "equipo-sorpresas-tenemos"}, {"valor": 1, "palabra": "sorpresas-tenemos-ustedes"}, {"valor": 1, "palabra": "tenemos-ustedes-segunda"}, {"valor": 1, "palabra": "ustedes-segunda-edición"}, {"valor": 1, "palabra": "segunda-edición-temática"}, {"valor": 1, "palabra": "edición-temática-nuestro"}, {"valor": 1, "palabra": "temática-nuestro-ciclista"}, {"valor": 1, "palabra": "nuestro-ciclista-prepara"}, {"valor": 1, "palabra": "ciclista-prepara-celular"}, {"valor": 1, "palabra": "prepara-celular-muchas"}, {"valor": 1, "palabra": "celular-muchas-pásatelo"}, {"valor": 1, "palabra": "muchas-pásatelo-grande"}, {"valor": 1, "palabra": "pásatelo-grande-seguridad"}, {"valor": 1, "palabra": "grande-seguridad-esfuerzo"}, {"valor": 1, "palabra": "seguridad-esfuerzo-coordinación"}]}, "2024-02-03-2024-02-03": {"MEX - Cuajimalpa - FB": [{"valor": 1, "palabra": "buenas-noches-descansen"}, {"valor": 1, "palabra": "noches-descansen-adrian"}, {"valor": 1, "palabra": "descansen-adrian-rubalcava"}, {"valor": 1, "palabra": "adrian-rubalcava-puedes"}, {"valor": 1, "palabra": "rubalcava-puedes-encontrarlos"}, {"valor": 1, "palabra": "puedes-encontrarlos-deportivo"}, {"valor": 1, "palabra": "encontrarlos-deportivo-experiencia"}, {"valor": 1, "palabra": "deportivo-experiencia-instalaciones"}, {"valor": 1, "palabra": "experiencia-instalaciones-entrenamientos"}, {"valor": 1, "palabra": "instalaciones-entrenamientos-bastante"}, {"valor": 1, "palabra": "entrenamientos-bastante-completos"}, {"valor": 1, "palabra": "bastante-completos-adrian"}, {"valor": 1, "palabra": "completos-adrian-rubalcava"}], "MEX - Azcapotzalco - FB": [{"valor": 7, "palabra": "alcaldesa-margarita-saldaña"}, {"valor": 3, "palabra": "margarita-saldaña-hernández"}, {"valor": 2, "palabra": "mantente-informado-nuestras"}, {"valor": 2, "palabra": "informado-nuestras-sociales"}, {"valor": 2, "palabra": "tuvimos-sábado-unidad"}, {"valor": 2, "palabra": "saldaña-hernández-realizó"}, {"valor": 2, "palabra": "hernández-realizó-entrega"}, {"valor": 2, "palabra": "realizó-entrega-realizadas"}, {"valor": 2, "palabra": "entrega-realizadas-parque"}, {"valor": 2, "palabra": "realizadas-parque-prohogar"}, {"valor": 2, "palabra": "parque-prohogar-continúa"}, {"valor": 2, "palabra": "prohogar-continúa-programa"}, {"valor": 2, "palabra": "continúa-programa-recuperación"}, {"valor": 2, "palabra": "programa-recuperación-espacios"}, {"valor": 2, "palabra": "recuperación-espacios-encuentra"}, {"valor": 2, "palabra": "espacios-encuentra-óptimas"}, {"valor": 2, "palabra": "encuentra-óptimas-condiciones"}, {"valor": 2, "palabra": "óptimas-condiciones-vecinos"}, {"valor": 2, "palabra": "condiciones-vecinos-puedan"}, {"valor": 2, "palabra": "vecinos-puedan-disfrutarlo"}, {"valor": 2, "palabra": "puedan-disfrutarlo-azcapotzalco"}, {"valor": 2, "palabra": "disfrutarlo-azcapotzalco-avanzando"}, {"valor": 2, "palabra": "participación-activa-comunidad"}, {"valor": 2, "palabra": "activa-comunidad-presencia"}, {"valor": 2, "palabra": "comunidad-presencia-alcaldesa"}, {"valor": 2, "palabra": "presencia-alcaldesa-margarita"}, {"valor": 1, "palabra": "contribuciones-celebramos-estamos"}, {"valor": 1, "palabra": "celebramos-estamos-mejorando"}, {"valor": 1, "palabra": "estamos-mejorando-ambiente"}, {"valor": 1, "palabra": "mejorando-ambiente-también"}], "MEX - Miguel Hidalgo - FB": [{"valor": 2, "palabra": "recuerda-sombra-whatsapp"}, {"valor": 1, "palabra": "cuenten-porque-pasarán"}, {"valor": 1, "palabra": "porque-pasarán-nuestros"}, {"valor": 1, "palabra": "pasarán-nuestros-paseos"}, {"valor": 1, "palabra": "nuestros-paseos-ciclistas"}, {"valor": 1, "palabra": "paseos-ciclistas-temáticos"}, {"valor": 1, "palabra": "ciclistas-temáticos-mañana"}, {"valor": 1, "palabra": "temáticos-mañana-transmisión"}, {"valor": 1, "palabra": "mañana-transmisión-espero"}, {"valor": 1, "palabra": "transmisión-espero-acompáñenme"}, {"valor": 1, "palabra": "espero-acompáñenme-disfruta"}, {"valor": 1, "palabra": "acompáñenme-disfruta-sábado"}, {"valor": 1, "palabra": "disfruta-sábado-implementa"}, {"valor": 1, "palabra": "sábado-implementa-tranquilidad"}, {"valor": 1, "palabra": "implementa-tranquilidad-nuestros"}, {"valor": 1, "palabra": "tranquilidad-nuestros-visitantes"}, {"valor": 1, "palabra": "nuestros-visitantes-recuerda"}, {"valor": 1, "palabra": "visitantes-recuerda-sombra"}, {"valor": 1, "palabra": "sombra-whatsapp-colonia"}, {"valor": 1, "palabra": "whatsapp-colonia-ampliación"}, {"valor": 1, "palabra": "colonia-ampliación-daniel"}, {"valor": 1, "palabra": "ampliación-daniel-vecinos"}, {"valor": 1, "palabra": "daniel-vecinos-decidieron"}, {"valor": 1, "palabra": "vecinos-decidieron-beneficiar"}, {"valor": 1, "palabra": "decidieron-beneficiar-comunidad"}, {"valor": 1, "palabra": "beneficiar-comunidad-luminarias"}, {"valor": 1, "palabra": "comunidad-luminarias-duplicará"}, {"valor": 1, "palabra": "luminarias-duplicará-presupuesto"}, {"valor": 1, "palabra": "duplicará-presupuesto-participativo"}, {"valor": 1, "palabra": "presupuesto-participativo-además"}]}, "2024-02-04-2024-02-04": {"MEX - Cuajimalpa - FB": [{"valor": 2, "palabra": "adrian-rubalcava-alcaldía"}, {"valor": 2, "palabra": "rubalcava-alcaldía-cuajimalpa"}, {"valor": 2, "palabra": "alcaldía-cuajimalpa-morelos"}, {"valor": 2, "palabra": "cumpleaños-muchas-felicidades"}, {"valor": 2, "palabra": "hacemos-extensivas-nuestras"}, {"valor": 2, "palabra": "extensivas-nuestras-condolencias"}, {"valor": 2, "palabra": "nuestras-condolencias-familiares"}, {"valor": 2, "palabra": "condolencias-familiares-amigos"}, {"valor": 2, "palabra": "muchas-felicidades-muchas"}, {"valor": 2, "palabra": "felicidades-muchas-felicidades"}, {"valor": 1, "palabra": "conurbada-problemas-graves"}, {"valor": 1, "palabra": "problemas-graves-abastecimiento"}, {"valor": 1, "palabra": "graves-abastecimiento-derivado"}, {"valor": 1, "palabra": "abastecimiento-derivado-lluvia"}, {"valor": 1, "palabra": "derivado-lluvia-colonias"}, {"valor": 1, "palabra": "lluvia-colonias-gastan"}, {"valor": 1, "palabra": "colonias-gastan-buenas"}, {"valor": 1, "palabra": "gastan-buenas-noches"}, {"valor": 1, "palabra": "buenas-noches-unidad"}, {"valor": 1, "palabra": "noches-unidad-manejo"}, {"valor": 1, "palabra": "unidad-manejo-ambiental"}, {"valor": 1, "palabra": "manejo-ambiental-peteretes"}, {"valor": 1, "palabra": "ambiental-peteretes-desierto"}, {"valor": 1, "palabra": "peteretes-desierto-leones"}, {"valor": 1, "palabra": "desierto-leones-adrian"}, {"valor": 1, "palabra": "leones-adrian-rubalcava"}, {"valor": 1, "palabra": "cuajimalpa-morelos-extiende"}, {"valor": 1, "palabra": "morelos-extiende-cordial"}, {"valor": 1, "palabra": "extiende-cordial-felicitación"}, {"valor": 1, "palabra": "cordial-felicitación-alicia"}], "MEX - Azcapotzalco - FB": [{"valor": 4, "palabra": "alcaldesa-margarita-saldaña"}, {"valor": 3, "palabra": "programa-recuperación-espacios"}, {"valor": 3, "palabra": "vecinos-puedan-disfrutarlo"}, {"valor": 3, "palabra": "margarita-saldaña-hernández"}, {"valor": 2, "palabra": "saldaña-hernández-realizó"}, {"valor": 2, "palabra": "hernández-realizó-entrega"}, {"valor": 2, "palabra": "realizó-entrega-realizadas"}, {"valor": 2, "palabra": "entrega-realizadas-parque"}, {"valor": 2, "palabra": "realizadas-parque-prohogar"}, {"valor": 2, "palabra": "parque-prohogar-continúa"}, {"valor": 2, "palabra": "prohogar-continúa-programa"}, {"valor": 2, "palabra": "continúa-programa-recuperación"}, {"valor": 2, "palabra": "recuperación-espacios-encuentra"}, {"valor": 2, "palabra": "espacios-encuentra-óptimas"}, {"valor": 2, "palabra": "encuentra-óptimas-condiciones"}, {"valor": 2, "palabra": "óptimas-condiciones-vecinos"}, {"valor": 2, "palabra": "condiciones-vecinos-puedan"}, {"valor": 2, "palabra": "puedan-disfrutarlo-azcapotzalco"}, {"valor": 2, "palabra": "disfrutarlo-azcapotzalco-avanzando"}, {"valor": 2, "palabra": "entrega-trabajos-parque"}, {"valor": 2, "palabra": "trabajos-parque-deportivo"}, {"valor": 2, "palabra": "parque-deportivo-margarita"}, {"valor": 2, "palabra": "deportivo-margarita-juárez"}, {"valor": 2, "palabra": "margarita-juárez-tezozomoc"}, {"valor": 2, "palabra": "juárez-tezozomoc-azcapotzalco"}, {"valor": 2, "palabra": "maestra-margarita-saldaña"}, {"valor": 1, "palabra": "estamos-parque-juárez"}, {"valor": 1, "palabra": "parque-juárez-continuamos"}, {"valor": 1, "palabra": "juárez-continuamos-programa"}, {"valor": 1, "palabra": "continuamos-programa-recuperación"}], "MEX - Miguel Hidalgo - FB": [{"valor": 31, "palabra": "buenas-noches-alcalde"}, {"valor": 20, "palabra": "alcalde-buenas-noches"}, {"valor": 11, "palabra": "noches-alcalde-buenas"}, {"valor": 6, "palabra": "buenas-noches-saludos"}, {"valor": 6, "palabra": "noches-alcalde-saludos"}, {"valor": 5, "palabra": "alcalde-saludos-buenas"}, {"valor": 5, "palabra": "saludos-buenas-noches"}, {"valor": 4, "palabra": "buenas-noches-buenas"}, {"valor": 4, "palabra": "noches-buenas-noches"}, {"valor": 4, "palabra": "saludos-alcalde-gracias"}, {"valor": 4, "palabra": "buenas-tardes-alcalde"}, {"valor": 3, "palabra": "saludos-alcalde-buenas"}, {"valor": 2, "palabra": "gobierno-ciudad-cuando"}, {"valor": 2, "palabra": "noches-alcalde-excelente"}, {"valor": 2, "palabra": "alcalde-mauricio-buenas"}, {"valor": 2, "palabra": "noches-saludos-alcalde"}, {"valor": 2, "palabra": "trabajo-buenas-noches"}, {"valor": 2, "palabra": "puestos-ambulantes-puente"}, {"valor": 2, "palabra": "saludos-buenas-tardes"}, {"valor": 2, "palabra": "tardes-alcalde-saludos"}, {"valor": 2, "palabra": "querido-alcalde-saludos"}, {"valor": 2, "palabra": "vecinos-ampliación-daniel"}, {"valor": 2, "palabra": "excelente-alcalde-buenas"}, {"valor": 2, "palabra": "noches-alcalde-mauricio"}, {"valor": 2, "palabra": "alcalde-saludos-alcalde"}, {"valor": 2, "palabra": "noches-alcalde-alcalde"}, {"valor": 2, "palabra": "buenas-noches-gracias"}, {"valor": 1, "palabra": "espero-disfrutado-ciclista"}, {"valor": 1, "palabra": "disfrutado-ciclista-organizamos"}, {"valor": 1, "palabra": "ciclista-organizamos-hacerlo"}]}, "2024-02-05-2024-02-05": {"MEX - Cuajimalpa - FB": [{"valor": 1, "palabra": "personal-dejando-reparar"}, {"valor": 1, "palabra": "dejando-reparar-juárez"}, {"valor": 1, "palabra": "reparar-juárez-estimado"}, {"valor": 1, "palabra": "juárez-estimado-adrian"}, {"valor": 1, "palabra": "estimado-adrian-rubalcava"}, {"valor": 1, "palabra": "adrian-rubalcava-juárez"}, {"valor": 1, "palabra": "rubalcava-juárez-cuándo"}, {"valor": 1, "palabra": "juárez-cuándo-litros"}, {"valor": 1, "palabra": "cuándo-litros-desperdiciados"}, {"valor": 1, "palabra": "litros-desperdiciados-cuajimalpa"}, {"valor": 1, "palabra": "desperdiciados-cuajimalpa-gracias"}, {"valor": 1, "palabra": "cuajimalpa-gracias-complejos"}, {"valor": 1, "palabra": "gracias-complejos-inmobiliarios"}, {"valor": 1, "palabra": "complejos-inmobiliarios-permitiste"}, {"valor": 1, "palabra": "inmobiliarios-permitiste-seguirás"}, {"valor": 1, "palabra": "permitiste-seguirás-permitiendo"}, {"valor": 1, "palabra": "seguirás-permitiendo-cambio"}, {"valor": 1, "palabra": "permitiendo-cambio-partido"}, {"valor": 1, "palabra": "cambio-partido-acciones"}, {"valor": 1, "palabra": "partido-acciones-contra"}, {"valor": 1, "palabra": "acciones-contra-pueblo"}, {"valor": 1, "palabra": "contra-pueblo-favoreciendo"}, {"valor": 1, "palabra": "pueblo-favoreciendo-quienes"}, {"valor": 1, "palabra": "favoreciendo-quienes-tienen"}, {"valor": 1, "palabra": "quienes-tienen-guapote"}, {"valor": 1, "palabra": "tienen-guapote-tienes"}, {"valor": 1, "palabra": "guapote-tienes-carisma"}, {"valor": 1, "palabra": "tienes-carisma-tenemos"}, {"valor": 1, "palabra": "carisma-tenemos-memoria"}, {"valor": 1, "palabra": "tenemos-memoria-muchas"}], "MEX - Azcapotzalco - FB": [{"valor": 1, "palabra": "nuestras-calles-diferentes"}, {"valor": 1, "palabra": "calles-diferentes-estamos"}, {"valor": 1, "palabra": "diferentes-estamos-dejando"}, {"valor": 1, "palabra": "estamos-dejando-tantos"}, {"valor": 1, "palabra": "dejando-tantos-abandono"}, {"valor": 1, "palabra": "tantos-abandono-soluciones"}, {"valor": 1, "palabra": "abandono-soluciones-acciones"}, {"valor": 1, "palabra": "soluciones-acciones-nuestros"}, {"valor": 1, "palabra": "acciones-nuestros-vecinos"}, {"valor": 1, "palabra": "nuestros-vecinos-alcaldía"}, {"valor": 1, "palabra": "vecinos-alcaldía-azcapotzalco"}, {"valor": 1, "palabra": "alcaldía-azcapotzalco-atiende"}, {"valor": 1, "palabra": "azcapotzalco-atiende-reporte"}, {"valor": 1, "palabra": "atiende-reporte-tiradero"}, {"valor": 1, "palabra": "reporte-tiradero-clandestino"}, {"valor": 1, "palabra": "tiradero-clandestino-calzada"}, {"valor": 1, "palabra": "clandestino-calzada-ángeles"}, {"valor": 1, "palabra": "calzada-ángeles-colonia"}, {"valor": 1, "palabra": "ángeles-colonia-martín"}, {"valor": 1, "palabra": "colonia-martín-xochinahuac"}, {"valor": 1, "palabra": "martín-xochinahuac-recordemos"}, {"valor": 1, "palabra": "xochinahuac-recordemos-responsabilidad"}, {"valor": 1, "palabra": "recordemos-responsabilidad-mantener"}, {"valor": 1, "palabra": "responsabilidad-mantener-entorno"}, {"valor": 1, "palabra": "mantener-entorno-limpio"}, {"valor": 1, "palabra": "entorno-limpio-porque"}, {"valor": 1, "palabra": "limpio-porque-letreros"}, {"valor": 1, "palabra": "porque-letreros-genial"}, {"valor": 1, "palabra": "letreros-genial-cuando"}, {"valor": 1, "palabra": "genial-cuando-genera"}], "MEX - Miguel Hidalgo - FB": [{"valor": 3, "palabra": "alcalde-mauricio-echartea"}, {"valor": 2, "palabra": "nuestras-vecinas-vecinos"}, {"valor": 2, "palabra": "alcaldía-miguel-hidalgo"}, {"valor": 2, "palabra": "secretaría-seguridad-ciudadana"}, {"valor": 1, "palabra": "impunidad-fiscalía-quienes"}, {"valor": 1, "palabra": "fiscalía-quienes-confianza"}, {"valor": 1, "palabra": "quienes-confianza-nuestras"}, {"valor": 1, "palabra": "confianza-nuestras-vecinas"}, {"valor": 1, "palabra": "vecinas-vecinos-alcaldía"}, {"valor": 1, "palabra": "vecinos-alcaldía-miguel"}, {"valor": 1, "palabra": "miguel-hidalgo-gracias"}, {"valor": 1, "palabra": "hidalgo-gracias-tenemos"}, {"valor": 1, "palabra": "gracias-tenemos-equipo"}, {"valor": 1, "palabra": "tenemos-equipo-mujeres"}, {"valor": 1, "palabra": "equipo-mujeres-hombres"}, {"valor": 1, "palabra": "mujeres-hombres-camiseta"}, {"valor": 1, "palabra": "hombres-camiseta-servicio"}, {"valor": 1, "palabra": "camiseta-servicio-público"}, {"valor": 1, "palabra": "servicio-público-entregados"}, {"valor": 1, "palabra": "público-entregados-cuerpo"}, {"valor": 1, "palabra": "entregados-cuerpo-además"}, {"valor": 1, "palabra": "cuerpo-además-resultados"}, {"valor": 1, "palabra": "además-resultados-secretaría"}, {"valor": 1, "palabra": "resultados-secretaría-seguridad"}, {"valor": 1, "palabra": "seguridad-ciudadana-informa"}, {"valor": 1, "palabra": "ciudadana-informa-tercera"}, {"valor": 1, "palabra": "informa-tercera-semana"}, {"valor": 1, "palabra": "tercera-semana-logrado"}, {"valor": 1, "palabra": "semana-logrado-inhibir"}, {"valor": 1, "palabra": "logrado-inhibir-chelerías"}]}}